galgebra/__init__.py
galgebra/_version.py
galgebra/atoms.py
galgebra/deprecated.py
galgebra/dop.py
galgebra/ga.py
galgebra/lt.py
galgebra/metric.py
galgebra/mv.py
galgebra/printer.py
galgebra/utils.py
galgebra/_backports/__init__.py
galgebra/_backports/typing.py
galgebra/_utils/__init__.py
galgebra/_utils/cached_property.py
galgebra/_utils/kwarg_parser.py
galgebra/_utils/parser.py
galgebra/_utils/printable.py
test/__init__.py
test/test_differential_ops.py
test/test_lt.py
test/test_misc.py
test/test_mv.py
test/test_printer.py
test/test_test.py
galgebra-0.5.2.dist-info/LICENSE
galgebra-0.5.2.dist-info/METADATA
galgebra-0.5.2.dist-info/WHEEL
galgebra-0.5.2.dist-info/top_level.txt
galgebra-0.5.2.dist-info/RECORD
