Metadata-Version: 2.1
Name: galgebra
Version: 0.5.2
Summary: Symbolic Geometric Algebra/Calculus package for SymPy.
Home-page: https://github.com/pygae/galgebra
Author: Alan Bromborsky
Maintainer: Hugo Hadfield
Maintainer-email: hadfield.hugo@gmail.com
License: BSD
Project-URL: Documentation, http://galgebra.readthedocs.io
Project-URL: Bug Tracker, https://github.com/pygae/galgebra/issues
Project-URL: Source Code, https://github.com/pygae/galgebra
Classifier: Development Status :: 4 - Beta
Classifier: Environment :: Console
Classifier: Intended Audience :: Science/Research
Classifier: License :: OSI Approved :: BSD License
Classifier: Natural Language :: English
Classifier: Operating System :: OS Independent
Classifier: Programming Language :: Python :: 3.8
Classifier: Programming Language :: Python :: 3.9
Classifier: Programming Language :: Python :: 3.10
Classifier: Programming Language :: Python :: 3.11
Classifier: Topic :: Scientific/Engineering :: Mathematics
Classifier: Topic :: Scientific/Engineering :: Physics
Requires-Python: >=3.6
License-File: LICENSE
Requires-Dist: sympy
